{
  "teamstoolkit.accountTree.azureAccountTooltip": "AZURE ACCOUNT  \nTeams ツールキットでは、プロジェクトの Azure リソースをデプロイするために Azure サブスクリプションが必要になる場合があります。",
  "teamstoolkit.accountTree.m365AccountTooltip": "M365 ACCOUNT  \nTeams ツールキットには、Teams が実行されていて登録されている Microsoft 365 の組織アカウントが必要です。",
  "teamstoolkit.accountTree.noSubscriptions": "サブスクリプションが見つかりません",
  "teamstoolkit.accountTree.noSubscriptionsTooltip": "サブスクリプションがありません。リソースを Azure にプロビジョニングまたはデプロイすることはできません。",
  "teamstoolkit.accountTree.sideloadingJoinM365": "M365 開発者プログラムに参加する",
  "teamstoolkit.accountTree.sideloadingMessage": "[Teams ツールキット] Microsoft 365 テナント管理者がアカウントのサイドローディング アクセス許可を有効にしていません。アプリを Teams にインストールすることはできません。Microsoft 開発者プログラムに参加して、Microsoft 365 開発者テナントに申し込むか、テナント管理者に問い合わせて問題を解決してください。",
  "teamstoolkit.accountTree.sideloadingPass": "サイドローディングが有効",
  "teamstoolkit.accountTree.sideloadingPassTooltip": "サイドローディング アクセス許可は既に持っています。アプリを Teams にインストールすることをお勧めします。",
  "teamstoolkit.accountTree.sideloadingRefresh": "最新の情報に更新",
  "teamstoolkit.accountTree.sideloadingWarning": "サイドローディングが無効",
  "teamstoolkit.accountTree.sideloadingWarningTooltip": "M365 テナント管理者が、アカウントのサイドローディング アクセス許可を有効にしていません。アプリを Teams にインストールすることはできません。",
  "teamstoolkit.accountTree.signingInAzure": "Azure: サインインしています...",
  "teamstoolkit.accountTree.signingInM365": "M365: サインインしています...",
  "teamstoolkit.accountTree.specifySubscription": "サブスクリプションの指定",
  "teamstoolkit.accountTree.totalSubscriptions": "%d 個のサブスクリプションが検出されました",
  "teamstoolkit.appStudioLogin.learnMore": "詳細情報",
  "teamstoolkit.appStudioLogin.loginCancel": "サインインが取り消されました。Teams ツールキットには、Teams が実行され、登録されている Microsoft 365 の組織アカウントが必要です。",
  "teamstoolkit.appStudioLogin.message": "Teams ツールキットには、Teams が実行され、登録されている Microsoft 365 の組織アカウントが必要です。必要に応じて、M365 開発者プログラムから無料のテスト アカウントを作成できます。",
  "teamstoolkit.azureLogin.failToFindSubscription": "サブスクリプションが見つかりませんでした。",
  "teamstoolkit.azureLogin.message": "Teams ツールキットには、プロジェクトの Azure リソースをデプロイするための Azure アカウントとサブスクリプションが必要です。それ以上の確認を行わなければ課金されません。",
  "teamstoolkit.azureLogin.noSubscriptionFound": "NoSubscriptionFound",
  "teamstoolkit.azureLogin.selectSubscription": "サブスクリプションの選択",
  "teamstoolkit.azureLogin.subscription": "サブスクリプション",
  "teamstoolkit.azureLogin.unknownSubscription": "サブスクリプションを設定できません。アクセスできるサブスクリプションを選択します。",
  "teamstoolkit.cacheAccess.readHomeAccountIdFail": "ホーム アカウント ID の読み取りに失敗しました: ",
  "teamstoolkit.cacheAccess.readTokenFail": "トークンの読み取りが失敗しました: ",
  "teamstoolkit.cacheAccess.saveHomeAccountIdFail": "ホーム アカウント ID の保存に失敗しました: ",
  "teamstoolkit.cacheAccess.saveTokenFail": "トークンの保存に失敗しました: ",
  "teamstoolkit.cacheAccess.writeTokenFail": "書き込みトークンが失敗しました: ",
  "teamstoolkit.codeFlowLogin.loginCodeFlowFailureDescription": "トークン交換のログイン コードを取得できません。別のアカウントでログインします。",
  "teamstoolkit.codeFlowLogin.loginCodeFlowFailureTitle": "LoginCodeFail",
  "teamstoolkit.codeFlowLogin.loginComponent": "ログイン",
  "teamstoolkit.codeFlowLogin.loginFailureDescription": "ユーザー ログイン情報を取得できません。別のアカウントでログインします。",
  "teamstoolkit.codeFlowLogin.loginFailureTitle": "LoginFail",
  "teamstoolkit.codeFlowLogin.loginPortConflictDescription": "ログイン ポートの待機中にタイムアウトが発生しました。もう一度やり直してください。",
  "teamstoolkit.codeFlowLogin.loginPortConflictTitle": "LoginPortConflict",
  "teamstoolkit.codeFlowLogin.loginTimeoutDescription": "ログインの待機中にタイムアウトしました。もう一度やり直してください。",
  "teamstoolkit.codeFlowLogin.loginTimeoutTitle": "LoginTimeout",
  "teamstoolkit.codeFlowLogin.resultFileNotFound": "結果ファイルが見つかりません。",
  "teamstoolkit.codeFlowLogin.silentAcquireToken": "トークンをサイレントにで取得できませんでした: %s",
  "teamstoolkit.commands.accounts.title": "Teams: アカウント",
  "teamstoolkit.commands.accountsLink.title": "アカウントに関する詳細情報",
  "teamstoolkit.commands.addAppOwner.title": "M365 Teams アプリ (AAD アプリを使用) 所有者を追加する",
  "teamstoolkit.commands.addCapability.title": "Teams: 機能の追加",
  "teamstoolkit.commands.addCloudResource.title": "Teams: クラウド リソースの追加",
  "teamstoolkit.commands.addCICDWorkflows.title": "Teams: CI/CD ワークフローの追加",
  "teamstoolkit.commands.createEnvironment.title": "Teams: 新しい環境の作成",
  "teamstoolkit.commands.createProject.title": "Teams: 新しい Teams アプリの作成",
  "teamstoolkit.commands.debug.title": "Teams アプリの選択と Teams アプリのデバッグの開始",
  "teamstoolkit.commands.deploy.title": "Teams: クラウドに展開する",
  "teamstoolkit.commands.deploymentLink.title": "デプロイの詳細情報",
  "teamstoolkit.commands.devPortal.title": "Teams: Teams の開発者ポータル",
  "teamstoolkit.commands.developmentLink.title": "開発に関する詳細情報",
  "teamstoolkit.commands.document.title": "Teams: ドキュメント",
  "teamstoolkit.commands.editManifest.title": "Teams: マニフェスト ファイルの編集",
  "teamstoolkit.commands.environmentsLink.title": "環境に関する詳細情報",
  "teamstoolkit.commands.feedbackLink.title": "ヘルプとフィードバックに関する詳細情報",
  "teamstoolkit.commands.listAppOwner.title": "M365 Teams アプリ所有者を (AAD アプリを使用) を一覧表示する",
  "teamstoolkit.commands.localDebug.title": "ローカル デバッグ",
  "teamstoolkit.commands.migrateApp.title": "Teams: Outlook と Office アプリをサポートするために Teams JS SDK リファレンスをアップグレードする",
  "teamstoolkit.commands.migrateManifest.title": "Teams: Outlook と Office アプリをサポートするように Teams マニフェストをアップグレードする",
  "teamstoolkit.commands.openInPortal.title": "Portal で開く",
  "teamstoolkit.commands.openManifestSchema.title": "マニフェスト スキーマを開く",
  "teamstoolkit.commands.previewApp.title": "プレビュー アプリ",
  "teamstoolkit.commands.previewManifest.title": "マニフェスト ファイルのプレビュー",
  "teamstoolkit.commands.provision.title": "Teams: クラウドでプロビジョニングする",
  "teamstoolkit.commands.publish.title": "Teams: Teams に公開する",
  "teamstoolkit.commands.quickStart.title": "Teams: クイック スタート",
  "teamstoolkit.commands.refresh.title": "最新の情報に更新",
  "teamstoolkit.commands.reportIssue.title": "Teams: GitHub で問題を報告する",
  "teamstoolkit.commands.signInGuideline.title": "Teams 開発アカウントに関する詳細情報",
  "teamstoolkit.commands.signOut.title": "サインアウト",
  "teamstoolkit.commands.specifySubscription.title": "サブスクリプションの指定",
  "teamstoolkit.commands.survey.title": "Teams: アンケート",
  "teamstoolkit.commands.updateManifest.title": "Teams: マニフェストを Teams プラットフォームに更新する",
  "teamstoolkit.commands.upgradeProject.title": "Teams: プロジェクトのアップグレード",
  "teamstoolkit.commands.validateManifest.title": "Teams: マニフェスト ファイルの検証",
  "teamstoolkit.commands.viewSamples.title": "Teams: サンプルを表示する",
  "teamstoolkit.commands.zipPackage.title": "Teams: Zip Teams メタデータ パッケージ",
  "teamstoolkit.commandsTreeViewProvider.accountsDescription": "アカウント リスト",
  "teamstoolkit.commandsTreeViewProvider.accountsTitle": "アカウント",
  "teamstoolkit.commandsTreeViewProvider.active": "(アクティブ)",
  "teamstoolkit.commandsTreeViewProvider.addCapabilitiesDescription": "Teams アプリに追加機能を追加する",
  "teamstoolkit.commandsTreeViewProvider.addCapabilitiesTitle": "機能の追加",
  "teamstoolkit.commandsTreeViewProvider.addCapabilitiesTitleNew": "機能の追加",
  "teamstoolkit.commandsTreeViewProvider.addResourcesDescription": "Teams アプリに Azure リソースをさらに追加する",
  "teamstoolkit.commandsTreeViewProvider.addResourcesTitle": "リソースの追加",
  "teamstoolkit.commandsTreeViewProvider.addResourcesTitleNew": "クラウド リソースの追加",
  "teamstoolkit.commandsTreeViewProvider.appManagementDescription": "Teams アプリの管理",
  "teamstoolkit.commandsTreeViewProvider.appManagementTitle": "Teams アプリの管理",
  "teamstoolkit.commandsTreeViewProvider.azureAccountNotMatch": "サインインしている Azure アカウントには、前のプロビジョニングで使用したサブスクリプション '%s' にアクセスするためのアクセス許可がありません。サインアウトし、正しい Azure アカウントでサインインしてください。",
  "teamstoolkit.commandsTreeViewProvider.azureAccountNotSignedIn": "サインインしている Azure アカウントはありません。Azure にサインインしてください。",
  "teamstoolkit.commandsTreeViewProvider.botManagementDescription": "Teams ボットの管理",
  "teamstoolkit.commandsTreeViewProvider.botManagementTitle": "Teams ボットの管理",
  "teamstoolkit.commandsTreeViewProvider.buildPackageDescription": "公開用のパッケージに Teams アプリをビルドする",
  "teamstoolkit.commandsTreeViewProvider.buildPackageTitle": "Teams パッケージのビルド",
  "teamstoolkit.commandsTreeViewProvider.buildPackageTitleNew": "Zip Teams メタデータ パッケージ",
  "teamstoolkit.commandsTreeViewProvider.createProjectDescription": "新しい Teams アプリを最初から作成するか、サンプル アプリから開始する",
  "teamstoolkit.commandsTreeViewProvider.createProjectTitle": "新しいプロジェクトの作成",
  "teamstoolkit.commandsTreeViewProvider.createProjectTitleNew": "新しい Teams アプリを作成する",
  "teamstoolkit.commandsTreeViewProvider.deployDescription": "Azure でプロビジョニングされたリソースに Teams アプリをデプロイする",
  "teamstoolkit.commandsTreeViewProvider.deployTitle": "クラウドへのデプロイ",
  "teamstoolkit.commandsTreeViewProvider.deployTitleNew": "クラウドへのデプロイ",
  "teamstoolkit.commandsTreeViewProvider.documentationDescription": "ツールキットを使用して Teams アプリをビルドする方法について説明します",
  "teamstoolkit.commandsTreeViewProvider.documentationTitle": "ドキュメント",
  "teamstoolkit.commandsTreeViewProvider.emptyM365Tenant": "環境状態ファイルのテナント ID が空です。再プロビジョニングして、もう一度お試しください",
  "teamstoolkit.commandsTreeViewProvider.feedbackDescription": "フィードバックの送信",
  "teamstoolkit.commandsTreeViewProvider.feedbackTitle": "フィードバック",
  "teamstoolkit.commandsTreeViewProvider.getStartDescription": "Teamsfx での概要",
  "teamstoolkit.commandsTreeViewProvider.initProjectDescription": "既存のアプリケーションを初期化する",
  "teamstoolkit.commandsTreeViewProvider.initProjectTitleNew": "既存のアプリケーションを初期化する",
  "teamstoolkit.commandsTreeViewProvider.m365AccountNotMatch": "サインインしている M365 アカウントが、前のプロビジョニングで使用された M365 テナントと一致しません。サインアウトし、正しい M365 アカウントでサインインしてください。",
  "teamstoolkit.commandsTreeViewProvider.m365AccountNotSignedIn": "サインインしている M365 アカウントがありません。M365 にサインインしてください。",
  "teamstoolkit.commandsTreeViewProvider.m365TenantNotMatch": "M365 テナント ID (以前にプロビジョニングするために使用) が現在のアカウントと一致しません。",
  "teamstoolkit.commandsTreeViewProvider.manifestEditorDescription": "Teams アプリ マニフェストを編集する",
  "teamstoolkit.commandsTreeViewProvider.manifestEditorTitle": "マニフェスト エディター",
  "teamstoolkit.commandsTreeViewProvider.manifestEditorTitleNew": "マニフェスト ファイルの編集",
  "teamstoolkit.commandsTreeViewProvider.previewACDescription": "Visual Studio Code でアダプティブ カードを直接プレビューおよび作成する",
  "teamstoolkit.commandsTreeViewProvider.previewAdaptiveCard": "アダプティブ カードのプレビューとデバッグ",
  "teamstoolkit.commandsTreeViewProvider.projectDescription": "プロジェクトを管理する",
  "teamstoolkit.commandsTreeViewProvider.projectTitle": "PROJECT",
  "teamstoolkit.commandsTreeViewProvider.provisionDescription": "Azure で Teams アプリ リソースをプロビジョニングする",
  "teamstoolkit.commandsTreeViewProvider.provisionTitle": "クラウドでのプロビジョニング",
  "teamstoolkit.commandsTreeViewProvider.provisionTitleNew": "クラウドでのプロビジョニング",
  "teamstoolkit.commandsTreeViewProvider.publishDescription": "Teams に公開する",
  "teamstoolkit.commandsTreeViewProvider.publishTitle": "Teams に公開する",
  "teamstoolkit.commandsTreeViewProvider.quickStartDescription": "Teams アプリのビルドを開始するための簡単なヒント",
  "teamstoolkit.commandsTreeViewProvider.quickStartTitle": "クイック スタート",
  "teamstoolkit.commandsTreeViewProvider.reportIssuesDescription": "問題を報告し、フィードバックをお寄せください",
  "teamstoolkit.commandsTreeViewProvider.reportIssuesTitle": "問題の報告",
  "teamstoolkit.commandsTreeViewProvider.reportIssuesTitleNew": "GitHub で問題を報告する",
  "teamstoolkit.commandsTreeViewProvider.samplesDescription": "サンプル ギャラリーのサンプルを使用して開始する",
  "teamstoolkit.commandsTreeViewProvider.samplesTitle": "サンプル",
  "teamstoolkit.commandsTreeViewProvider.samplesTitleNew": "サンプルを表示",
  "teamstoolkit.commandsTreeViewProvider.teamsDevCenterDescription": "Teamsfx での概要",
  "teamstoolkit.commandsTreeViewProvider.teamsDevCenterTitle": "TEAMS デベロッパー センター",
  "teamstoolkit.commandsTreeViewProvider.addCICDWorkflowsTitle": "CI/CD ワークフローの追加",
  "teamstoolkit.commandsTreeViewProvider.addCICDWorkflowsDescription": "Github、Azure DevOps、Jenkins のワークフロー自動化テンプレートを作成する",
  "teamstoolkit.commandsTreeViewProvider.teamsDevPortalDescription": "Teams アプリの登録を管理し、その他のツールにアクセスする",
  "teamstoolkit.commandsTreeViewProvider.teamsDevPortalTitle": "開発者ポータルに移動",
  "teamstoolkit.commandsTreeViewProvider.teamsDevPortalTitleNew": "Teams の開発者ポータル",
  "teamstoolkit.commandsTreeViewProvider.teamstoolkit.commandsTreeViewProvider.getStartTitle": "概要",
  "teamstoolkit.commandsTreeViewProvider.validateManifestDescription": "Teams アプリ マニフェスト ファイルを検証する",
  "teamstoolkit.commandsTreeViewProvider.validateManifestTitle": "アプリ マニフェスト ファイルの検証",
  "teamstoolkit.commandsTreeViewProvider.validateManifestTitleNew": "マニフェスト ファイルを検証する",
  "teamstoolkit.common.cancel": "キャンセル",
  "teamstoolkit.common.confirm": "確認",
  "teamstoolkit.common.readMore": "関連資料",
  "teamstoolkit.common.signOutOf": "'%s' からサインアウトしますか?",
  "teamstoolkit.common.signin": "サインイン",
  "teamstoolkit.common.signout": "サインアウト",
  "teamstoolkit.common.userCancel": "ユーザーのキャンセル",
  "teamstoolkit.envTree.subscriptionTooltip": "'%s' 環境は Azure サブスクリプション '%s' でプロビジョニングされています (ID: %s)",
  "teamstoolkit.envTree.subscriptionTooltipWithoutName": "'%s' 環境は Azure サブスクリプション '%s' でプロビジョニングされています",
  "teamstoolkit.graphLogin.warningMsg": "Teams ツールキットには、Microsoft 365 アカウントが必要です。これは、Microsoft Teams にログインするのに使用するアカウントです。Teams ツールキットでは、このアカウントを使用してアプリケーションとサービス プリンシパルを管理します。",
  "teamstoolkit.handlers.automaticNpmInstall": "Teams ツールキットは、プロジェクトに必要なパッケージを自動的にインストールします。実行の詳細を表示するには、コマンド ウィンドウプロンプトを参照してください。下のボタンをクリックして \"自動 NPM インストール\" をオフにすることで、これを無効にすることもできます。",
  "teamstoolkit.handlers.azureSignIn": "Azure アカウントに正常にサインインしました。",
  "teamstoolkit.handlers.azureSignOut": "Azure アカウントから正常にサインアウトしました。",
  "teamstoolkit.handlers.concurrentTriggerTask": "タスク '%s' はまだ実行中です。完了するまで待ってから、別のタスクを開始します。",
  "teamstoolkit.handlers.configTitle": "場所の変更",
  "teamstoolkit.handlers.coreNotReady": "コア モジュールが読み込まれています",
  "teamstoolkit.handlers.createProjectNotification": "新しい Teams アプリを作成するか、既存のアプリを開いて README ファイルを開く必要があります。",
  "teamstoolkit.handlers.createProjectTitle": "新しい Teams アプリを作成する",
  "teamstoolkit.handlers.decryptFailed": "シークレットの暗号化を解除できませんでした。",
  "teamstoolkit.handlers.disableAutomaticNpmInstall": "自動 NPM インストールを無効にする",
  "teamstoolkit.handlers.editSecretTitle": "暗号化解除されたシークレット値を編集する",
  "teamstoolkit.handlers.fileNotFound": "%s が見つかりません。開けません。",
  "teamstoolkit.handlers.findEnvFailed": "プロジェクト環境 %s が見つかりません。",
  "teamstoolkit.handlers.getHelp": "ヘルプを受ける",
  "teamstoolkit.handlers.grantPermissionSucceeded": "Teams アプリの所有者として環境 '%s' にアカウント '%s' を追加しました。",
  "teamstoolkit.handlers.grantPermissionWarning": "追加されたユーザーが Azure リソースにアクセスできない場合は、Azure portal を使用してアクセス ポリシーを手動で設定する必要があります。 ",
  "teamstoolkit.handlers.grantPermissionWarningSpfx": "追加されたユーザーが SharePoint アプリ カタログ サイト管理者でない場合は、SharePoint 管理センターを使用してアクセス ポリシーを手動でセットアップする必要があります。 ",
  "teamstoolkit.handlers.installAdaptiveCardExt": "アダプティブ カードをプレビューおよびデバッグするには、\"Adaptive Card Studio\" 拡張機能を使用することをお勧めします。",
  "teamstoolkit.handlers.invalidProject": "Teams アプリをデバッグできませんでした。プロジェクトは有効な Teams プロジェクトではありません。",
  "teamstoolkit.handlers.localDebugDescription": "プロジェクトは %s で正常に作成されました (設定で既定の場所を変更できます)。引き続きアプリのローカル デバッグを実行できます。",
  "teamstoolkit.handlers.localDebugTitle": "ローカル デバッグ",
  "teamstoolkit.handlers.logErrorFormat": "コード: ${e.source}.${e.name}, メッセージ: ${e.message}, スタック: ${e.stack}",
  "teamstoolkit.handlers.loginFailed": "ログインに失敗しました。操作は終了します。",
  "teamstoolkit.handlers.m365SignIn": "M365 アカウントに正常にサインインしました。",
  "teamstoolkit.handlers.m365SignOut": "M365 アカウントから正常にサインアウトしました。",
  "teamstoolkit.handlers.noOpenWorkspace": "開いているワークスペースがありません",
  "teamstoolkit.handlers.openFolderTitle": "フォルダーを開く",
  "teamstoolkit.handlers.operationNotSupport": "操作はサポートされていません: %s",
  "teamstoolkit.handlers.provisionBeforeGrantOrListPermission": "Teams アプリがまだプロビジョニングされていないため、所有者を追加または一覧表示できません。下の [リソースのプロビジョニング] ボタンをクリックして Teams アプリを登録してください。",
  "teamstoolkit.handlers.provisionResourcesButton": "リソースのプロビジョニング",
  "teamstoolkit.handlers.referLinkForMoreDetails": "詳細については、このリンクを参照してください。 ",
  "teamstoolkit.handlers.reportIssue": "問題を報告",
  "teamstoolkit.handlers.resourceInfoNotFound": "環境 %s の %s 情報を読み込めません。",
  "teamstoolkit.handlers.signIn365": "M365 にサインインする",
  "teamstoolkit.handlers.signInAzure": "Azure にサインイン",
  "teamstoolkit.handlers.signInAzureNew": "Azure にサインインする (省略可能)",
  "teamstoolkit.handlers.signOutOfAzure": "Azure からサインアウトする: ",
  "teamstoolkit.handlers.signOutOfM365": "M365 からサインアウトする: ",
  "teamstoolkit.handlers.stateFileNotFound": "状態ファイルが環境 %s に見つかりません。関連する状態ファイルを生成するには、まず 'クラウドでプロビジョニング' を実行する必要があります。",
  "teamstoolkit.handlers.teamsAppIdNotFound": "'state.%s.json' で 'fx-resource-appstudio.teamsAppId' が見つかりませんでした。",
  "teamstoolkit.handlers.teamsToolkit": "Teams ツールキット",
  "teamstoolkit.handlers.vsCodeEnvironment": "VS Code 環境: %s",
  "teamstoolkit.localDebug.installApp.cancel": "キャンセル",
  "teamstoolkit.localDebug.installApp.continue": "続行",
  "teamstoolkit.localDebug.installApp.description": "Outlook でアプリケーションのデバッグを続行するには、まず Teams を使用してアプリをインストールする必要があります。\n\n",
  "teamstoolkit.localDebug.installApp.detection": "まず、Teams にアプリをインストールしていないことを検出しました。アプリがインストールされていることを確認してください。\n\n",
  "teamstoolkit.localDebug.installApp.guide": "[Teams にインストール] をクリックすると、アプリをインストールするための Teams Web クライアントがポップアップ表示されます。完了したら、戻って [続行] をクリックします。",
  "teamstoolkit.localDebug.installApp.installInTeams": "Teams にインストールする",
  "teamstoolkit.localDebug.learnMore": "詳細情報",
  "teamstoolkit.localDebug.npmInstallFailedHintMessage": "タスク '%s' が失敗しました。詳細なエラー情報については、'%s' ターミナル ウィンドウを参照するか、[問題の報告] ボタンをクリックして問題を報告してください。",
  "teamstoolkit.localDebug.openSettings": "設定を開く",
  "teamstoolkit.localDebug.portAlreadyInUse": "ポート: %s は既に使用されています。このポートを閉じてから、もう一度やり直してください。",
  "teamstoolkit.localDebug.portWarning": "package.json でポートを変更すると、ローカル デバッグが中断される可能性があります。[詳細情報] ボタンをクリックして、すべてのポートの変更が想定されていることを確認するか、ドキュメントを参照してください。(%s package.json の場所: %s)",
  "teamstoolkit.localDebug.portsAlreadyInUse": "ポート: %s は既に使用されています。これらのポートを閉じてから、もう一度やり直してください。",
  "teamstoolkit.localDebug.prerequisitesCheckFailure": "前提条件を確認するときにエラーが発生します。詳細なエラー メッセージについては、出力ウィンドウを参照してください。(チェックに失敗しました: %s)",
  "teamstoolkit.migrateTeamsManifest.progressTitle": "Outlook と Office で Teams マニフェストをアップグレードして拡張する",
  "teamstoolkit.migrateTeamsManifest.selectFileConfig.name": "アップグレードする Teams マニフェストの選択",
  "teamstoolkit.migrateTeamsManifest.selectFileConfig.title": "アップグレードする Teams マニフェストの選択",
  "teamstoolkit.migrateTeamsManifest.success": "Teams マニフェスト %s が正常にアップグレードされました。",
  "teamstoolkit.migrateTeamsManifest.updateManifest": "Teams マニフェストを更新します。",
  "teamstoolkit.migrateTeamsManifest.upgrade": "アップグレード",
  "teamstoolkit.migrateTeamsManifest.warningMessage": "Teams Toolkit では、選択した Teams マニフェスト ファイルが、Outlook と Office で動作するように更新されます。アップグレードする前に、ファイルの変更をより適切に追跡するために Git を使用することをお勧めします。",
  "teamstoolkit.migrateTeamsTabApp.progressTitle": "Outlook と Office で Teams タブ アプリをアップグレードして拡張する",
  "teamstoolkit.migrateTeamsTabApp.selectFolderConfig.name": "アップグレードする Teams タブ アプリの選択",
  "teamstoolkit.migrateTeamsTabApp.selectFolderConfig.title": "アップグレードする Teams タブ アプリの選択",
  "teamstoolkit.migrateTeamsTabApp.success": "Teams タブ アプリ %s が正常にアップグレードされました。",
  "teamstoolkit.migrateTeamsTabApp.updateCodeError": "ファイル %s コード: %s、メッセージ: %s で更新できませんでした。",
  "teamstoolkit.migrateTeamsTabApp.updateCodesErrorMessage": "%d ファイルを更新できませんでした: %s など。詳細については、出力チャネルを参照してください。",
  "teamstoolkit.migrateTeamsTabApp.updateCodesErrorOutput": "%d ファイルを更新できませんでした: %s。",
  "teamstoolkit.migrateTeamsTabApp.updatePackageJsonWarning": "%s に @microsoft/teams-js 依存関係が見つかりませんでした。アップグレードするものはありません。",
  "teamstoolkit.migrateTeamsTabApp.updatingCode": "%s で %s コードを更新しています。",
  "teamstoolkit.migrateTeamsTabApp.updatingCodes": "@microsoft/teams-js v2 を使用するようにコードを更新しています。",
  "teamstoolkit.migrateTeamsTabApp.updatingPackageJson": "@microsoft/teams-js v2 を使用するように package.json を更新しています。",
  "teamstoolkit.migrateTeamsTabApp.upgrade": "アップグレード",
  "teamstoolkit.migrateTeamsTabApp.warningMessage": "Teams ツールキットは、Teams クライアント SDK v2 を使用するように選択した Teams タブ アプリをインプレースで更新します。アップグレードする前に、ファイルの変更をより適切に追跡するために Git を使用することをお勧めします。",
  "teamstoolkit.preview.launchTeamsApp": "Teams アプリを起動する準備をしています...",
  "teamstoolkit.preview.prepareTeamsApp": "Teams アプリの登録を準備しています...",
  "teamstoolkit.preview.progressTitle": "Teams アプリのプレビュー",
  "teamstoolkit.progressHandler.prepareTask": " タスクを準備します。",
  "teamstoolkit.progressHandler.reloadNotice": "%s%s%s (注意: ウィンドウを再度読み込んで、タスクに時間がかかりすぎる場合は再試行できます)。",
  "teamstoolkit.progressHandler.teamsToolkitComponent": "[Teams ツールキット]",
  "teamstoolkit.qm.emptySelection": "選択オプションが空です",
  "teamstoolkit.qm.multiSelectKeyboard": " (チェック/チェックを外すには Space キー)",
  "teamstoolkit.qm.ok": "OK (Enter)",
  "teamstoolkit.qm.selectFileOrFolder": "ファイル/フォルダーの選択",
  "teamstoolkit.survey.banner.message": "userAsked",
  "teamstoolkit.survey.banner.title": "Teams ツールキット拡張機能に関するフィードバックはありますか?",
  "teamstoolkit.survey.cancelMessage": "userCancelled",
  "teamstoolkit.survey.dontShowAgain.message": "dontShowAgain",
  "teamstoolkit.survey.dontShowAgain.title": "今後表示しない",
  "teamstoolkit.survey.remindMeLater.message": "remindMeLater",
  "teamstoolkit.survey.remindMeLater.title": "後で通知する",
  "teamstoolkit.survey.takeSurvey.message": "takeSurvey",
  "teamstoolkit.survey.takeSurvey.title": "アンケートの実施",
  "teamstoolkit.upgrade.banner": "Teams ツールキットが v%s に更新されました - 新機能をご確認ください。",
  "teamstoolkit.upgrade.whatIsNewTitle": "新機能",
  "teamstoolkit.upgradeToMultiEnvAndBicep.learnMoreLink": "https://aka.ms/teamsfx-existing-aad-doc",
  "teamstoolkit.upgradeToMultiEnvAndBicep.learnMoreText": "詳細情報",
  "teamstoolkit.upgradeToMultiEnvAndBicep.outputMsg": "\"AAD_APP_CLIENT_SECRET\" = \"%s\" をシステム環境変数に設定します。詳細については、この Wiki (%s) を参照してください。",
  "teamstoolkit.upgradeToMultiEnvAndBicep.showMsg": "システム環境変数に \"AAD_APP_CLIENT_SECRET\" = \"%s\" を設定してください\\n詳細については、[詳細情報] をクリックすることもできます。",
  "teamstoolkit.userInterface.noQuestionDescription": "質問の説明はありません",
  "teamstoolkit.userInterface.notImplementQuestion": "質問するには、この型を実装しません。",
  "teamstoolkit.userInterface.showSuccessfully": "正常に表示",
  "teamstoolkit.webview.downloadFrom": "%s からのダウンロード",
  "teamstoolkit.webview.downloadSampleFail": "サンプル アプリをダウンロードできませんでした",
  "teamstoolkit.webview.downloadSampleTitle": "サンプル アプリをダウンロードするフォルダーを選択する",
  "teamstoolkit.webview.emptyData": "空の zip ファイル",
  "teamstoolkit.webview.fetchData": "サンプル アプリをフェッチする",
  "teamstoolkit.webview.folderExist": "フォルダーは既に存在します",
  "teamstoolkit.webview.folderExistDialogTitle": "パス %s は既に存在します。別のフォルダーを選択します。",
  "teamstoolkit.webview.invalidFolder": "フォルダーが無効です",
  "teamstoolkit.webview.quickStartPageTitle": "クイック スタート",
  "teamstoolkit.webview.samplePageTitle": "サンプル",
  "teamstoolkit.webview.surveyPageTitle": "Teams ツールキットに関するアンケート",
  "teamstoolkit.webview.unzipPackage": "サンプル パッケージの解凍",
  "teamstoolkit.PrerequisitesValidationError": "前提条件の確認に失敗しました。上記のすべての問題を修正してから、ローカル デバッグをもう一度実行してください。前提条件の確認とインストールをバイパスする場合は、Visual Studio Code 設定で無効にすることができます。"
}